mkvinfo/__init__.py
mkvinfo/_errors.py
mkvinfo/_types.py
mkvinfo/_utils.py
mkvinfo/py.typed
mkvinfo-0.0.3.dist-info/METADATA
mkvinfo-0.0.3.dist-info/WHEEL
mkvinfo-0.0.3.dist-info/licenses/LICENSE
mkvinfo-0.0.3.dist-info/RECORD
