Metadata-Version: 2.4
Name: mkvinfo
Version: 0.0.3
Summary: Python library for probing matroska files with mkvmerge.
Project-URL: Repository, https://github.com/Ravencentric/mkvinfo
Project-URL: Documentation, https://ravencentric.cc/mkvinfo/
Author-email: Ravencentric <me@ravencentric.cc>
License-File: LICENSE
Classifier: Operating System :: OS Independent
Classifier: Programming Language :: Python :: 3.10
Classifier: Programming Language :: Python :: 3.11
Classifier: Programming Language :: Python :: 3.12
Classifier: Programming Language :: Python :: 3.13
Classifier: Programming Language :: Python :: 3.14
Classifier: Typing :: Typed
Requires-Python: >=3.10
Requires-Dist: pydantic>=2.12.1
